[{"date":"2025-10-20","time":"01:20","flight":[{"no":"3S 629","airline":"BOX"}],"origin_dest":["DWC","FRA"],"status":"Dep 01:30","gate_baggage":"","terminal":"","isArrival":false,"isCargo":true,"_raw":{"aisle":"","hall":""}},{"date":"2025-10-27","time":"06:45","flight":[{"no":"3S 629","airline":"BOX"}],"origin_dest":["DWC","FRA"],"status":"Dep 06:05","gate_baggage":"","terminal":"","isArrival":false,"isCargo":true,"_raw":{"aisle":"","hall":""}},{"date":"2025-11-03","time":"06:45","flight":[{"no":"3S 629","airline":"BOX"}],"origin_dest":["DWC","FRA"],"status":"Dep 07:25","gate_baggage":"","terminal":"","isArrival":false,"isCargo":true,"_raw":{"aisle":"","hall":""}},{"date":"2025-11-10","time":"06:45","flight":[{"no":"3S 629","airline":"BOX"}],"origin_dest":["DWC","FRA"],"status":"Dep 06:11","gate_baggage":"","terminal":"","isArrival":false,"isCargo":true,"_raw":{"aisle":"","hall":""}},{"date":"2025-11-17","time":"06:45","flight":[{"no":"3S 629","airline":"BOX"}],"origin_dest":["DWC","FRA"],"status":"Dep 06:01","gate_baggage":"","terminal":"","isArrival":false,"isCargo":true,"_raw":{"aisle":"","hall":""}},{"date":"2025-11-24","time":"06:45","flight":[{"no":"3S 629","airline":"BOX"}],"origin_dest":["DWC","FRA"],"status":"Dep 05:52","gate_baggage":"","terminal":"","isArrival":false,"isCargo":true,"_raw":{"aisle":"","hall":""}},{"date":"2025-12-01","time":"06:45","flight":[{"no":"3S 629","airline":"BOX"}],"origin_dest":["DWC","FRA"],"status":"Dep 06:39","gate_baggage":"","terminal":"","isArrival":false,"isCargo":true,"_raw":{"aisle":"","hall":""}},{"date":"2025-12-08","time":"06:45","flight":[{"no":"3S 629","airline":"BOX"}],"origin_dest":["DWC","FRA"],"status":"Dep 06:06","gate_baggage":"","terminal":"","isArrival":false,"isCargo":true,"_raw":{"aisle":"","hall":""}},{"date":"2025-12-15","time":"06:45","flight":[{"no":"3S 629","airline":"BOX"}],"origin_dest":["DWC","FRA"],"status":"Dep 06:13","gate_baggage":"","terminal":"","isArrival":false,"isCargo":true,"_raw":{"aisle":"","hall":""}},{"date":"2025-12-22","time":"06:45","flight":[{"no":"3S 629","airline":"BOX"}],"origin_dest":["DWC","FRA"],"status":"Dep 06:21","gate_baggage":"","terminal":"","isArrival":false,"isCargo":true,"_raw":{"aisle":"","hall":""}},{"date":"2025-12-29","time":"06:45","flight":[{"no":"3S 629","airline":"BOX"}],"origin_dest":["DWC","FRA"],"status":"Dep 05:51","gate_baggage":"","terminal":"","isArrival":false,"isCargo":true,"_raw":{"aisle":"","hall":""}},{"date":"2026-01-05","time":"06:45","flight":[{"no":"3S 629","airline":"BOX"}],"origin_dest":["DWC","FRA"],"status":"Dep 06:08","gate_baggage":"","terminal":"","isArrival":false,"isCargo":true,"_raw":{"aisle":"","hall":""}},{"date":"2026-01-12","time":"06:45","flight":[{"no":"3S 629","airline":"BOX"}],"origin_dest":["DWC","FRA"],"status":"Dep 05:59","gate_baggage":"","terminal":"","isArrival":false,"isCargo":true,"_raw":{"aisle":"","hall":""}}]