[
  {
    "date": "2025-10-28",
    "time": "18:50",
    "flight": [
      {
        "no": "7L 1247",
        "airline": "AZG"
      }
    ],
    "origin_dest": [
      "GYD"
    ],
    "status": "Dep 20:45",
    "gate_baggage": "",
    "terminal": "",
    "isArrival": false,
    "isCargo": true,
    "_raw": {
      "aisle": "",
      "hall": ""
    }
  },
  {
    "date": "2025-10-29",
    "time": "15:50",
    "flight": [
      {
        "no": "7L 1247",
        "airline": "AZG"
      }
    ],
    "origin_dest": [
      "GYD"
    ],
    "status": "Cancelled",
    "gate_baggage": "",
    "terminal": "",
    "isArrival": false,
    "isCargo": true,
    "_raw": {
      "aisle": "",
      "hall": ""
    }
  },
  {
    "date": "2025-11-04",
    "time": "21:30",
    "flight": [
      {
        "no": "7L 1247",
        "airline": "AZG"
      }
    ],
    "origin_dest": [
      "GYD"
    ],
    "status": "Dep 22:44",
    "gate_baggage": "",
    "terminal": "",
    "isArrival": false,
    "isCargo": true,
    "_raw": {
      "aisle": "",
      "hall": ""
    }
  },
  {
    "date": "2025-11-14",
    "time": "00:30",
    "flight": [
      {
        "no": "7L 1247",
        "airline": "AZG"
      }
    ],
    "origin_dest": [
      "GYD"
    ],
    "status": "Dep 23:41 (13/11/2025)",
    "gate_baggage": "",
    "terminal": "",
    "isArrival": false,
    "isCargo": true,
    "_raw": {
      "aisle": "",
      "hall": ""
    }
  },
  {
    "date": "2025-11-20",
    "time": "01:00",
    "flight": [
      {
        "no": "7L 1247",
        "airline": "AZG"
      }
    ],
    "origin_dest": [
      "GYD"
    ],
    "status": "Dep 17:03",
    "gate_baggage": "",
    "terminal": "",
    "isArrival": false,
    "isCargo": true,
    "_raw": {
      "aisle": "",
      "hall": ""
    }
  },
  {
    "date": "2025-12-02",
    "time": "21:00",
    "flight": [
      {
        "no": "7L 1247",
        "airline": "AZG"
      }
    ],
    "origin_dest": [
      "GYD"
    ],
    "status": "Dep 21:51",
    "gate_baggage": "",
    "terminal": "",
    "isArrival": false,
    "isCargo": true,
    "_raw": {
      "aisle": "",
      "hall": ""
    }
  },
  {
    "date": "2025-12-10",
    "time": "07:50",
    "flight": [
      {
        "no": "7L 1247",
        "airline": "AZG"
      }
    ],
    "origin_dest": [
      "GYD"
    ],
    "status": "Dep 16:35",
    "gate_baggage": "",
    "terminal": "",
    "isArrival": false,
    "isCargo": true,
    "_raw": {
      "aisle": "",
      "hall": ""
    }
  },
  {
    "date": "2025-12-18",
    "time": "01:40",
    "flight": [
      {
        "no": "7L 1247",
        "airline": "AZG"
      }
    ],
    "origin_dest": [
      "GYD"
    ],
    "status": "Dep 01:12",
    "gate_baggage": "",
    "terminal": "",
    "isArrival": false,
    "isCargo": true,
    "_raw": {
      "aisle": "",
      "hall": ""
    }
  },
  {
    "date": "2025-12-25",
    "time": "01:30",
    "flight": [
      {
        "no": "7L 1247",
        "airline": "AZG"
      }
    ],
    "origin_dest": [
      "DMM",
      "DWC",
      "GYD"
    ],
    "status": "Cancelled",
    "gate_baggage": "",
    "terminal": "",
    "isArrival": false,
    "isCargo": true,
    "_raw": {
      "aisle": "",
      "hall": ""
    }
  },
  {
    "date": "2025-12-26",
    "time": "03:05",
    "flight": [
      {
        "no": "7L 1247",
        "airline": "AZG"
      }
    ],
    "origin_dest": [
      "DMM",
      "DWC",
      "GYD"
    ],
    "status": "Dep 03:36",
    "gate_baggage": "",
    "terminal": "",
    "isArrival": false,
    "isCargo": true,
    "_raw": {
      "aisle": "",
      "hall": ""
    }
  },
  {
    "date": "2026-01-13",
    "time": "21:10",
    "flight": [
      {
        "no": "7L 1247",
        "airline": "AZG"
      }
    ],
    "origin_dest": [
      "GYD"
    ],
    "status": "Dep 21:09",
    "gate_baggage": "",
    "terminal": "",
    "isArrival": false,
    "isCargo": true,
    "_raw": {
      "aisle": "",
      "hall": ""
    }
  }
]
