[{"date":"2025-10-26","time":"23:40","flight":[{"no":"CX 021","airline":"CPA"}],"origin_dest":["SYD"],"status":"Dep 00:03 (27/10/2025)","gate_baggage":"","terminal":"","isArrival":false,"isCargo":true,"_raw":{"aisle":"","hall":""}},{"date":"2025-11-02","time":"23:40","flight":[{"no":"CX 021","airline":"CPA"}],"origin_dest":["SYD"],"status":"Dep 23:44","gate_baggage":"","terminal":"","isArrival":false,"isCargo":true,"_raw":{"aisle":"","hall":""}},{"date":"2025-11-09","time":"23:40","flight":[{"no":"CX 021","airline":"CPA"}],"origin_dest":["SYD"],"status":"Dep 23:46","gate_baggage":"","terminal":"","isArrival":false,"isCargo":true,"_raw":{"aisle":"","hall":""}},{"date":"2025-11-16","time":"23:40","flight":[{"no":"CX 021","airline":"CPA"}],"origin_dest":["SYD"],"status":"Dep 23:42","gate_baggage":"","terminal":"","isArrival":false,"isCargo":true,"_raw":{"aisle":"","hall":""}},{"date":"2025-11-23","time":"23:40","flight":[{"no":"CX 021","airline":"CPA"}],"origin_dest":["SYD"],"status":"Dep 23:45","gate_baggage":"","terminal":"","isArrival":false,"isCargo":true,"_raw":{"aisle":"","hall":""}},{"date":"2025-11-30","time":"23:40","flight":[{"no":"CX 021","airline":"CPA"}],"origin_dest":["SYD"],"status":"Dep 23:35","gate_baggage":"","terminal":"","isArrival":false,"isCargo":true,"_raw":{"aisle":"","hall":""}},{"date":"2025-12-07","time":"23:40","flight":[{"no":"CX 021","airline":"CPA"}],"origin_dest":["SYD"],"status":"Dep 23:46","gate_baggage":"","terminal":"","isArrival":false,"isCargo":true,"_raw":{"aisle":"","hall":""}},{"date":"2025-12-14","time":"23:40","flight":[{"no":"CX 021","airline":"CPA"}],"origin_dest":["SYD"],"status":"Dep 23:47","gate_baggage":"","terminal":"","isArrival":false,"isCargo":true,"_raw":{"aisle":"","hall":""}},{"date":"2025-12-21","time":"23:40","flight":[{"no":"CX 021","airline":"CPA"}],"origin_dest":["SYD"],"status":"Dep 23:36","gate_baggage":"","terminal":"","isArrival":false,"isCargo":true,"_raw":{"aisle":"","hall":""}},{"date":"2026-01-04","time":"23:40","flight":[{"no":"CX 021","airline":"CPA"}],"origin_dest":["SYD"],"status":"Dep 23:52","gate_baggage":"","terminal":"","isArrival":false,"isCargo":true,"_raw":{"aisle":"","hall":""}},{"date":"2026-01-11","time":"23:40","flight":[{"no":"CX 021","airline":"CPA"}],"origin_dest":["SYD"],"status":"Dep 23:44","gate_baggage":"","terminal":"","isArrival":false,"isCargo":true,"_raw":{"aisle":"","hall":""}}]