[
  {
    "date": "2025-10-18",
    "time": "20:45",
    "flight": [
      {
        "no": "CX 067",
        "airline": "CPA"
      }
    ],
    "origin_dest": [
      "DWC",
      "FRA"
    ],
    "status": "Dep 23:35",
    "gate_baggage": "",
    "terminal": "",
    "isArrival": false,
    "isCargo": true,
    "_raw": {
      "aisle": "",
      "hall": ""
    }
  },
  {
    "date": "2025-10-25",
    "time": "20:45",
    "flight": [
      {
        "no": "CX 067",
        "airline": "CPA"
      }
    ],
    "origin_dest": [
      "DWC",
      "FRA"
    ],
    "status": "Dep 21:15",
    "gate_baggage": "",
    "terminal": "",
    "isArrival": false,
    "isCargo": true,
    "_raw": {
      "aisle": "",
      "hall": ""
    }
  }
]
