[{"date":"2025-12-19","time":"23:30","flight":[{"no":"HX 545","airline":"CRK"}],"origin_dest":["DAD"],"status":"At gate 23:57","gate_baggage":"7","terminal":"","isArrival":true,"isCargo":false,"_raw":{"aisle":"","hall":"A"}},{"date":"2025-12-20","time":"23:30","flight":[{"no":"HX 545","airline":"CRK"}],"origin_dest":["DAD"],"status":"At gate 23:29","gate_baggage":"7","terminal":"","isArrival":true,"isCargo":false,"_raw":{"aisle":"","hall":"A"}},{"date":"2025-12-21","time":"23:30","flight":[{"no":"HX 545","airline":"CRK"},{"no":"EY 6818","airline":"ETD"}],"origin_dest":["DAD"],"status":"At gate 23:35","gate_baggage":"16","terminal":"","isArrival":true,"isCargo":false,"_raw":{"aisle":"","hall":"B"}},{"date":"2025-12-22","time":"23:30","flight":[{"no":"HX 545","airline":"CRK"},{"no":"EY 6818","airline":"ETD"}],"origin_dest":["DAD"],"status":"At gate 23:39","gate_baggage":"7","terminal":"","isArrival":true,"isCargo":false,"_raw":{"aisle":"","hall":"A"}},{"date":"2025-12-23","time":"23:30","flight":[{"no":"HX 545","airline":"CRK"},{"no":"EY 6818","airline":"ETD"}],"origin_dest":["DAD"],"status":"At gate 23:29","gate_baggage":"16","terminal":"","isArrival":true,"isCargo":false,"_raw":{"aisle":"","hall":"B"}},{"date":"2025-12-24","time":"23:30","flight":[{"no":"HX 545","airline":"CRK"},{"no":"EY 6818","airline":"ETD"}],"origin_dest":["DAD"],"status":"At gate 23:39","gate_baggage":"14","terminal":"","isArrival":true,"isCargo":false,"_raw":{"aisle":"","hall":"B"}},{"date":"2025-12-26","time":"23:30","flight":[{"no":"HX 545","airline":"CRK"},{"no":"EY 6818","airline":"ETD"}],"origin_dest":["DAD"],"status":"At gate 23:48","gate_baggage":"15","terminal":"","isArrival":true,"isCargo":false,"_raw":{"aisle":"","hall":"B"}},{"date":"2025-12-27","time":"23:30","flight":[{"no":"HX 545","airline":"CRK"},{"no":"EY 6818","airline":"ETD"}],"origin_dest":["DAD"],"status":"At gate 23:43","gate_baggage":"16","terminal":"","isArrival":true,"isCargo":false,"_raw":{"aisle":"","hall":"B"}},{"date":"2025-12-28","time":"23:30","flight":[{"no":"HX 545","airline":"CRK"},{"no":"EY 6818","airline":"ETD"}],"origin_dest":["DAD"],"status":"At gate 23:40","gate_baggage":"12","terminal":"","isArrival":true,"isCargo":false,"_raw":{"aisle":"","hall":"B"}},{"date":"2025-12-29","time":"23:30","flight":[{"no":"HX 545","airline":"CRK"},{"no":"EY 6818","airline":"ETD"}],"origin_dest":["DAD"],"status":"At gate 23:20","gate_baggage":"15","terminal":"","isArrival":true,"isCargo":false,"_raw":{"aisle":"","hall":"B"}},{"date":"2025-12-30","time":"23:30","flight":[{"no":"HX 545","airline":"CRK"},{"no":"EY 6818","airline":"ETD"}],"origin_dest":["DAD"],"status":"At gate 00:04 (31/12/2025)","gate_baggage":"16","terminal":"","isArrival":true,"isCargo":false,"_raw":{"aisle":"","hall":"B"}},{"date":"2025-12-31","time":"23:30","flight":[{"no":"HX 545","airline":"CRK"},{"no":"EY 6818","airline":"ETD"}],"origin_dest":["DAD"],"status":"At gate 23:48","gate_baggage":"16","terminal":"","isArrival":true,"isCargo":false,"_raw":{"aisle":"","hall":"B"}},{"date":"2026-01-02","time":"23:30","flight":[{"no":"HX 545","airline":"CRK"},{"no":"EY 6818","airline":"ETD"}],"origin_dest":["DAD"],"status":"At gate 23:38","gate_baggage":"16","terminal":"","isArrival":true,"isCargo":false,"_raw":{"aisle":"","hall":"B"}},{"date":"2026-01-03","time":"23:30","flight":[{"no":"HX 545","airline":"CRK"},{"no":"EY 6818","airline":"ETD"}],"origin_dest":["DAD"],"status":"At gate 23:54","gate_baggage":"14","terminal":"","isArrival":true,"isCargo":false,"_raw":{"aisle":"","hall":"B"}},{"date":"2026-01-04","time":"23:30","flight":[{"no":"HX 545","airline":"CRK"},{"no":"EY 6818","airline":"ETD"}],"origin_dest":["DAD"],"status":"At gate 23:26","gate_baggage":"7","terminal":"","isArrival":true,"isCargo":false,"_raw":{"aisle":"","hall":"A"}},{"date":"2026-01-05","time":"23:30","flight":[{"no":"HX 545","airline":"CRK"},{"no":"EY 6818","airline":"ETD"}],"origin_dest":["DAD"],"status":"At gate 23:24","gate_baggage":"13","terminal":"","isArrival":true,"isCargo":false,"_raw":{"aisle":"","hall":"B"}},{"date":"2026-01-09","time":"23:30","flight":[{"no":"HX 545","airline":"CRK"},{"no":"EY 6818","airline":"ETD"}],"origin_dest":["DAD"],"status":"At gate 23:32","gate_baggage":"7","terminal":"","isArrival":true,"isCargo":false,"_raw":{"aisle":"","hall":"A"}},{"date":"2026-01-12","time":"23:30","flight":[{"no":"HX 545","airline":"CRK"},{"no":"EY 6818","airline":"ETD"}],"origin_dest":["DAD"],"status":"At gate 23:38","gate_baggage":"15","terminal":"","isArrival":true,"isCargo":false,"_raw":{"aisle":"","hall":"B"}},{"date":"2026-01-19","time":"23:30","flight":[{"no":"HX 545","airline":"CRK"},{"no":"EY 6818","airline":"ETD"}],"origin_dest":["DAD"],"status":"At gate 23:27","gate_baggage":"15","terminal":"","isArrival":true,"isCargo":false,"_raw":{"aisle":"","hall":"B"}},{"date":"2026-01-20","time":"23:30","flight":[{"no":"HX 545","airline":"CRK"},{"no":"EY 6818","airline":"ETD"}],"origin_dest":["DAD"],"status":"At gate 23:55","gate_baggage":"15","terminal":"","isArrival":true,"isCargo":false,"_raw":{"aisle":"","hall":"B"}},{"date":"2026-01-21","time":"23:30","flight":[{"no":"HX 545","airline":"CRK"},{"no":"EY 6818","airline":"ETD"}],"origin_dest":["DAD"],"status":"At gate 23:29","gate_baggage":"6","terminal":"","isArrival":true,"isCargo":false,"_raw":{"aisle":"","hall":"A"}}]
