[{"date":"2025-10-16","time":"00:15","flight":[{"no":"UO 671","airline":"HKE"}],"origin_dest":["NGO"],"status":"At gate 23:57 (15/10/2025)","gate_baggage":"14","terminal":"","isArrival":true,"isCargo":false,"_raw":{"aisle":"","hall":"B"}},{"date":"2025-10-17","time":"00:15","flight":[{"no":"UO 671","airline":"HKE"}],"origin_dest":["NGO"],"status":"At gate 23:46 (16/10/2025)","gate_baggage":"16","terminal":"","isArrival":true,"isCargo":false,"_raw":{"aisle":"","hall":"B"}},{"date":"2025-10-18","time":"00:15","flight":[{"no":"UO 671","airline":"HKE"}],"origin_dest":["NGO"],"status":"At gate 23:53 (17/10/2025)","gate_baggage":"17","terminal":"","isArrival":true,"isCargo":false,"_raw":{"aisle":"","hall":"B"}},{"date":"2025-10-19","time":"00:15","flight":[{"no":"UO 671","airline":"HKE"}],"origin_dest":["NGO"],"status":"At gate 23:47 (18/10/2025)","gate_baggage":"16","terminal":"","isArrival":true,"isCargo":false,"_raw":{"aisle":"","hall":"B"}},{"date":"2025-10-20","time":"00:15","flight":[{"no":"UO 671","airline":"HKE"}],"origin_dest":["NGO"],"status":"At gate 23:54 (19/10/2025)","gate_baggage":"15","terminal":"","isArrival":true,"isCargo":false,"_raw":{"aisle":"","hall":"B"}},{"date":"2025-10-21","time":"00:15","flight":[{"no":"UO 671","airline":"HKE"}],"origin_dest":["NGO"],"status":"At gate 00:19","gate_baggage":"13","terminal":"","isArrival":true,"isCargo":false,"_raw":{"aisle":"","hall":"B"}},{"date":"2025-10-22","time":"00:15","flight":[{"no":"UO 671","airline":"HKE"}],"origin_dest":["NGO"],"status":"At gate 00:10","gate_baggage":"12","terminal":"","isArrival":true,"isCargo":false,"_raw":{"aisle":"","hall":"B"}},{"date":"2025-10-23","time":"00:15","flight":[{"no":"UO 671","airline":"HKE"}],"origin_dest":["NGO"],"status":"At gate 23:38 (22/10/2025)","gate_baggage":"17","terminal":"","isArrival":true,"isCargo":false,"_raw":{"aisle":"","hall":"B"}},{"date":"2025-10-24","time":"00:15","flight":[{"no":"UO 671","airline":"HKE"}],"origin_dest":["NGO"],"status":"At gate 23:47 (23/10/2025)","gate_baggage":"16","terminal":"","isArrival":true,"isCargo":false,"_raw":{"aisle":"","hall":"B"}},{"date":"2025-10-25","time":"00:15","flight":[{"no":"UO 671","airline":"HKE"}],"origin_dest":["NGO"],"status":"At gate 00:07","gate_baggage":"16","terminal":"","isArrival":true,"isCargo":false,"_raw":{"aisle":"","hall":"B"}},{"date":"2025-10-26","time":"00:15","flight":[{"no":"UO 671","airline":"HKE"}],"origin_dest":["NGO"],"status":"At gate 23:58 (25/10/2025)","gate_baggage":"17","terminal":"","isArrival":true,"isCargo":false,"_raw":{"aisle":"","hall":"B"}}]