[
  {
    "date": "2025-10-16",
    "time": "15:50",
    "flight": [
      {
        "no": "WI 8114",
        "airline": "WHT"
      }
    ],
    "origin_dest": [
      "CCU"
    ],
    "status": "Cancelled",
    "gate_baggage": "",
    "terminal": "",
    "isArrival": true,
    "isCargo": true,
    "_raw": {
      "aisle": "",
      "hall": ""
    }
  },
  {
    "date": "2025-10-22",
    "time": "19:25",
    "flight": [
      {
        "no": "WI 8114",
        "airline": "WHT"
      }
    ],
    "origin_dest": [
      "TBS",
      "DEL"
    ],
    "status": "Cancelled",
    "gate_baggage": "",
    "terminal": "",
    "isArrival": true,
    "isCargo": true,
    "_raw": {
      "aisle": "",
      "hall": ""
    }
  }
]
