[{"date":"2026-01-08","time":"15:35","flight":[{"no":"UO 684","airline":"HKE"},{"no":"CX 5684","airline":"CPA"}],"origin_dest":["NGO"],"status":"Dep 15:25","gate_baggage":"219","terminal":"T1","isArrival":false,"isCargo":false,"_raw":{"aisle":"H","hall":""}},{"date":"2026-01-08","time":"16:55","flight":[{"no":"UO 702","airline":"HKE"},{"no":"CX 5702","airline":"CPA"}],"origin_dest":["BKK"],"status":"Dep 17:20","gate_baggage":"219","terminal":"T1","isArrival":false,"isCargo":false,"_raw":{"aisle":"H","hall":""}},{"date":"2026-01-08","time":"19:15","flight":[{"no":"HX 169","airline":"CRK"},{"no":"HU 8271","airline":"CHH"}],"origin_dest":["SYX"],"status":"Dep 19:14","gate_baggage":"219","terminal":"T1","isArrival":false,"isCargo":false,"_raw":{"aisle":"K","hall":""}},{"date":"2026-01-08","time":"21:25","flight":[{"no":"UO 790","airline":"HKE"},{"no":"CX 5790","airline":"CPA"}],"origin_dest":["BKI"],"status":"Dep 21:25","gate_baggage":"219","terminal":"T1","isArrival":false,"isCargo":false,"_raw":{"aisle":"H","hall":""}},{"date":"2026-01-09","time":"08:00","flight":[{"no":"UO 130","airline":"HKE"},{"no":"CX 5130","airline":"CPA"}],"origin_dest":["KHH"],"status":"Dep 07:51","gate_baggage":"219","terminal":"T1","isArrival":false,"isCargo":false,"_raw":{"aisle":"H","hall":""}},{"date":"2026-01-09","time":"10:50","flight":[{"no":"HX 208","airline":"CRK"},{"no":"HU 8157","airline":"CHH"}],"origin_dest":["NKG"],"status":"Dep 10:46","gate_baggage":"219","terminal":"T1","isArrival":false,"isCargo":false,"_raw":{"aisle":"K","hall":""}},{"date":"2026-01-09","time":"14:15","flight":[{"no":"HX 610","airline":"CRK"},{"no":"TK 9208","airline":"THY"}],"origin_dest":["NRT"],"status":"Dep 14:29","gate_baggage":"219","terminal":"T1","isArrival":false,"isCargo":false,"_raw":{"aisle":"K","hall":""}},{"date":"2026-01-09","time":"16:50","flight":[{"no":"UO 558","airline":"HKE"},{"no":"CX 5558","airline":"CPA"}],"origin_dest":["DAD"],"status":"Dep 16:51","gate_baggage":"219","terminal":"T1","isArrival":false,"isCargo":false,"_raw":{"aisle":"H","hall":""}},{"date":"2026-01-09","time":"18:35","flight":[{"no":"HX 107","airline":"CRK"},{"no":"HU 8052","airline":"CHH"}],"origin_dest":["HAK"],"status":"Dep 18:50","gate_baggage":"219","terminal":"T1","isArrival":false,"isCargo":false,"_raw":{"aisle":"K","hall":""}},{"date":"2026-01-09","time":"20:55","flight":[{"no":"HX 304","airline":"CRK"},{"no":"HU 8160","airline":"CHH"}],"origin_dest":["PEK"],"status":"Dep 20:56","gate_baggage":"219","terminal":"T1","isArrival":false,"isCargo":false,"_raw":{"aisle":"K","hall":""}},{"date":"2026-01-10","time":"10:50","flight":[{"no":"HX 208","airline":"CRK"},{"no":"HU 8157","airline":"CHH"}],"origin_dest":["NKG"],"status":"Dep 10:49","gate_baggage":"219","terminal":"T1","isArrival":false,"isCargo":false,"_raw":{"aisle":"K","hall":""}},{"date":"2026-01-10","time":"13:40","flight":[{"no":"HX 264","airline":"CRK"},{"no":"BR 2900","airline":"EVA"}],"origin_dest":["TPE"],"status":"Dep 13:41","gate_baggage":"219","terminal":"T1","isArrival":false,"isCargo":false,"_raw":{"aisle":"K","hall":""}},{"date":"2026-01-10","time":"15:55","flight":[{"no":"HX 312","airline":"CRK"},{"no":"HU 8192","airline":"CHH"}],"origin_dest":["PEK"],"status":"Dep 15:44","gate_baggage":"219","terminal":"T1","isArrival":false,"isCargo":false,"_raw":{"aisle":"K","hall":""}},{"date":"2026-01-10","time":"18:15","flight":[{"no":"UO 182","airline":"HKE"},{"no":"CX 5182","airline":"CPA"}],"origin_dest":["RMQ"],"status":"Dep 18:11","gate_baggage":"219","terminal":"T1","isArrival":false,"isCargo":false,"_raw":{"aisle":"H","hall":""}},{"date":"2026-01-10","time":"20:20","flight":[{"no":"UO 748","airline":"HKE"},{"no":"CX 5748","airline":"CPA"}],"origin_dest":["PEN"],"status":"Dep 20:21","gate_baggage":"219","terminal":"T1","isArrival":false,"isCargo":false,"_raw":{"aisle":"H","hall":""}},{"date":"2026-01-11","time":"09:35","flight":[{"no":"HX 614","airline":"CRK"},{"no":"TK 8866","airline":"THY"},{"no":"EY 6809","airline":"ETD"}],"origin_dest":["KIX"],"status":"Dep 09:25","gate_baggage":"219","terminal":"T1","isArrival":false,"isCargo":false,"_raw":{"aisle":"K","hall":""}},{"date":"2026-01-11","time":"13:40","flight":[{"no":"HX 264","airline":"CRK"},{"no":"BR 2900","airline":"EVA"}],"origin_dest":["TPE"],"status":"Dep 13:37","gate_baggage":"219","terminal":"T1","isArrival":false,"isCargo":false,"_raw":{"aisle":"K","hall":""}},{"date":"2026-01-11","time":"15:50","flight":[{"no":"UO 826","airline":"HKE"},{"no":"CX 5826","airline":"CPA"}],"origin_dest":["OKA"],"status":"Dep 15:50","gate_baggage":"219","terminal":"T1","isArrival":false,"isCargo":false,"_raw":{"aisle":"H","hall":""}},{"date":"2026-01-11","time":"17:55","flight":[{"no":"UO 622","airline":"HKE"},{"no":"CX 5622","airline":"CPA"}],"origin_dest":["HND"],"status":"Dep 18:01","gate_baggage":"219","terminal":"T1","isArrival":false,"isCargo":false,"_raw":{"aisle":"H","hall":""}},{"date":"2026-01-12","time":"08:55","flight":[{"no":"UO 686","airline":"HKE"},{"no":"CX 5686","airline":"CPA"}],"origin_dest":["KIX"],"status":"Dep 08:52","gate_baggage":"219","terminal":"T1","isArrival":false,"isCargo":false,"_raw":{"aisle":"H","hall":""}},{"date":"2026-01-12","time":"11:50","flight":[{"no":"UO 898","airline":"HKE"},{"no":"CX 5898","airline":"CPA"}],"origin_dest":["KIX"],"status":"Dep 12:00","gate_baggage":"219","terminal":"T1","isArrival":false,"isCargo":false,"_raw":{"aisle":"H","hall":""}},{"date":"2026-01-12","time":"14:35","flight":[{"no":"HX 612","airline":"CRK"},{"no":"TK 9200","airline":"THY"},{"no":"EY 6808","airline":"ETD"}],"origin_dest":["KIX"],"status":"Dep 14:43","gate_baggage":"219","terminal":"T1","isArrival":false,"isCargo":false,"_raw":{"aisle":"K","hall":""}},{"date":"2026-01-12","time":"17:40","flight":[{"no":"HX 528","airline":"CRK"}],"origin_dest":["HAN"],"status":"Dep 17:40","gate_baggage":"219","terminal":"T1","isArrival":false,"isCargo":false,"_raw":{"aisle":"K","hall":""}},{"date":"2026-01-12","time":"18:20","flight":[{"no":"HX 232","airline":"CRK"}],"origin_dest":["PVG"],"status":"Dep 19:44","gate_baggage":"219","terminal":"T1","isArrival":false,"isCargo":false,"_raw":{"aisle":"K","hall":""}},{"date":"2026-01-12","time":"22:05","flight":[{"no":"UO 260","airline":"HKE"},{"no":"CX 5260","airline":"CPA"}],"origin_dest":["PKX"],"status":"Dep 21:55","gate_baggage":"219","terminal":"T1","isArrival":false,"isCargo":false,"_raw":{"aisle":"H","hall":""}},{"date":"2026-01-13","time":"00:55","flight":[{"no":"UO 616","airline":"HKE"}],"origin_dest":["ICN"],"status":"Dep 00:43","gate_baggage":"219","terminal":"T1","isArrival":false,"isCargo":false,"_raw":{"aisle":"H","hall":""}},{"date":"2026-01-13","time":"07:40","flight":[{"no":"UO 756","airline":"HKE"},{"no":"CX 5756","airline":"CPA"}],"origin_dest":["CNX"],"status":"Dep 07:43","gate_baggage":"219","terminal":"T1","isArrival":false,"isCargo":false,"_raw":{"aisle":"H","hall":""}},{"date":"2026-01-13","time":"09:40","flight":[{"no":"HX 640","airline":"CRK"},{"no":"EY 6807","airline":"ETD"}],"origin_dest":["FUK"],"status":"Dep 09:36","gate_baggage":"219","terminal":"T1","isArrival":false,"isCargo":false,"_raw":{"aisle":"K","hall":""}},{"date":"2026-01-13","time":"12:40","flight":[{"no":"HX 775","airline":"CRK"},{"no":"TK 9221","airline":"THY"}],"origin_dest":["BKK"],"status":"Dep 12:40","gate_baggage":"219","terminal":"T1","isArrival":false,"isCargo":false,"_raw":{"aisle":"K","hall":""}},{"date":"2026-01-13","time":"15:00","flight":[{"no":"HX 548","airline":"CRK"},{"no":"EY 6805","airline":"ETD"}],"origin_dest":["DAD"],"status":"Dep 15:00","gate_baggage":"219","terminal":"T1","isArrival":false,"isCargo":false,"_raw":{"aisle":"K","hall":""}},{"date":"2026-01-13","time":"16:55","flight":[{"no":"HX 765","airline":"CRK"},{"no":"TK 9224","airline":"THY"}],"origin_dest":["BKK"],"status":"Dep 16:50","gate_baggage":"219","terminal":"T1","isArrival":false,"isCargo":false,"_raw":{"aisle":"K","hall":""}},{"date":"2026-01-13","time":"20:55","flight":[{"no":"HX 304","airline":"CRK"},{"no":"HU 8160","airline":"CHH"}],"origin_dest":["PEK"],"status":"Dep 20:51","gate_baggage":"219","terminal":"T1","isArrival":false,"isCargo":false,"_raw":{"aisle":"K","hall":""}},{"date":"2026-01-14","time":"02:20","flight":[{"no":"UO 656","airline":"HKE"}],"origin_dest":["TAE"],"status":"Dep 02:12","gate_baggage":"219","terminal":"T1","isArrival":false,"isCargo":false,"_raw":{"aisle":"H","hall":""}},{"date":"2026-01-14","time":"07:25","flight":[{"no":"UO 724","airline":"HKE"},{"no":"CX 5724","airline":"CPA"}],"origin_dest":["HKT"],"status":"Dep 07:23","gate_baggage":"219","terminal":"T1","isArrival":false,"isCargo":false,"_raw":{"aisle":"H","hall":""}},{"date":"2026-01-14","time":"11:50","flight":[{"no":"HX 741","airline":"CRK"}],"origin_dest":["HKT"],"status":"Dep 12:16","gate_baggage":"219","terminal":"T1","isArrival":false,"isCargo":false,"_raw":{"aisle":"K","hall":""}},{"date":"2026-01-14","time":"15:05","flight":[{"no":"UO 114","airline":"HKE"},{"no":"CX 5114","airline":"CPA"}],"origin_dest":["TPE"],"status":"Dep 14:56","gate_baggage":"219","terminal":"T1","isArrival":false,"isCargo":false,"_raw":{"aisle":"H","hall":""}},{"date":"2026-01-14","time":"19:55","flight":[{"no":"UO 628","airline":"HKE"},{"no":"CX 5628","airline":"CPA"}],"origin_dest":["HND"],"status":"Dep 19:54","gate_baggage":"219","terminal":"T1","isArrival":false,"isCargo":false,"_raw":{"aisle":"H","hall":""}},{"date":"2026-01-15","time":"07:40","flight":[{"no":"UO 192","airline":"HKE"},{"no":"CX 5192","airline":"CPA"}],"origin_dest":["RMQ"],"status":"Dep 07:31","gate_baggage":"219","terminal":"T1","isArrival":false,"isCargo":false,"_raw":{"aisle":"H","hall":""}},{"date":"2026-01-15","time":"09:25","flight":[{"no":"HX 692","airline":"CRK"},{"no":"EY 6802","airline":"ETD"}],"origin_dest":["CTS"],"status":"Dep 10:08","gate_baggage":"219","terminal":"T1","isArrival":false,"isCargo":false,"_raw":{"aisle":"K","hall":""}},{"date":"2026-01-15","time":"11:55","flight":[{"no":"UO 746","airline":"HKE"},{"no":"CX 5746","airline":"CPA"}],"origin_dest":["PEN"],"status":"Dep 11:50","gate_baggage":"219","terminal":"T1","isArrival":false,"isCargo":false,"_raw":{"aisle":"H","hall":""}},{"date":"2026-01-15","time":"14:55","flight":[{"no":"UO 688","airline":"HKE"},{"no":"CX 5688","airline":"CPA"}],"origin_dest":["KIX"],"status":"Dep 14:47","gate_baggage":"219","terminal":"T1","isArrival":false,"isCargo":false,"_raw":{"aisle":"H","hall":""}},{"date":"2026-01-15","time":"16:35","flight":[{"no":"HX 260","airline":"CRK"},{"no":"BR 2896","airline":"EVA"}],"origin_dest":["TPE"],"status":"Est at 18:15","gate_baggage":"219","terminal":"T1","isArrival":false,"isCargo":false,"_raw":{"aisle":"K","hall":""}},{"date":"2026-01-15","time":"16:45","flight":[{"no":"UO 744","airline":"HKE"},{"no":"CX 5744","airline":"CPA"}],"origin_dest":["CNX"],"status":"Dep 16:54","gate_baggage":"219","terminal":"T1","isArrival":false,"isCargo":false,"_raw":{"aisle":"H","hall":""}},{"date":"2026-01-15","time":"19:50","flight":[{"no":"UO 226","airline":"HKE"},{"no":"CX 5226","airline":"CPA"}],"origin_dest":["NGB"],"status":"","gate_baggage":"219","terminal":"T1","isArrival":false,"isCargo":false,"_raw":{"aisle":"H","hall":""}},{"date":"2026-01-16","time":"09:00","flight":[{"no":"HX 236","airline":"CRK"},{"no":"HU 8492","airline":"CHH"}],"origin_dest":["PVG"],"status":"Dep 08:59","gate_baggage":"219","terminal":"T1","isArrival":false,"isCargo":false,"_raw":{"aisle":"K","hall":""}},{"date":"2026-01-16","time":"11:25","flight":[{"no":"HX 618","airline":"CRK"},{"no":"TK 8876","airline":"THY"},{"no":"EY 6811","airline":"ETD"}],"origin_dest":["KIX"],"status":"Dep 11:27","gate_baggage":"219","terminal":"T1","isArrival":false,"isCargo":false,"_raw":{"aisle":"K","hall":""}},{"date":"2026-01-16","time":"13:30","flight":[{"no":"UO 700","airline":"HKE"},{"no":"CX 5700","airline":"CPA"}],"origin_dest":["BKK"],"status":"Dep 13:31","gate_baggage":"219","terminal":"T1","isArrival":false,"isCargo":false,"_raw":{"aisle":"H","hall":""}},{"date":"2026-01-16","time":"15:55","flight":[{"no":"HX 312","airline":"CRK"},{"no":"HU 8192","airline":"CHH"}],"origin_dest":["PEK"],"status":"Dep 15:44","gate_baggage":"219","terminal":"T1","isArrival":false,"isCargo":false,"_raw":{"aisle":"K","hall":""}},{"date":"2026-01-16","time":"17:55","flight":[{"no":"UO 622","airline":"HKE"},{"no":"CX 5622","airline":"CPA"}],"origin_dest":["HND"],"status":"Dep 18:07","gate_baggage":"219","terminal":"T1","isArrival":false,"isCargo":false,"_raw":{"aisle":"H","hall":""}},{"date":"2026-01-16","time":"20:45","flight":[{"no":"HX 626","airline":"CRK"},{"no":"OZ 9296","airline":"AAR"}],"origin_dest":["ICN"],"status":"Dep 21:06","gate_baggage":"219","terminal":"T1","isArrival":false,"isCargo":false,"_raw":{"aisle":"K","hall":""}}]
